arcp/__init__.py
arcp/generate.py
arcp/parse.py
arcp-0.2.1.dist-info/LICENSE.txt
arcp-0.2.1.dist-info/METADATA
arcp-0.2.1.dist-info/WHEEL
arcp-0.2.1.dist-info/top_level.txt
arcp-0.2.1.dist-info/RECORD
