Metadata-Version: 1.1
Name: arcp
Version: 0.2.1
Summary: arcp (Archive and Package) URI parser and generator
Home-page: https://arcp.readthedocs.io/
Author: Stian Soiland-Reyes
Author-email: stain@apache.org
License: Apache License, Version 2.0
Download-URL: https://github.com/stain/arcp-py/archive/0.1.0.tar.gz
Keywords: arcp uri url iri archive package
Platform: UNKNOWN
Classifier: Development Status :: 3 - Alpha
Classifier: Intended Audience :: Developers
Classifier: Topic :: Software Development :: Build Tools
Classifier: Topic :: Software Development :: Libraries :: Python Modules
Classifier: Programming Language :: Python :: 2.7
Classifier: Programming Language :: Python :: 3
Classifier: Programming Language :: Python :: 3.5
Classifier: Programming Language :: Python :: 3.6
Classifier: Programming Language :: Python :: 3.7
Classifier: Programming Language :: Python :: 3.8
Classifier: Topic :: Internet
Classifier: Topic :: Internet :: WWW/HTTP
Classifier: Topic :: System :: Archiving
Classifier: Topic :: System :: Archiving :: Packaging
